writer/__init__.py
writer/abstract.py
writer/ai/__init__.py
writer/app_runner.py
writer/app_templates/default/.wf/components-blueprints_blueprint-0-0decp3w5erhvl0nw.jsonl
writer/app_templates/default/.wf/components-blueprints_root.jsonl
writer/app_templates/default/.wf/components-page-0-c0f99a9e-5004-4e75-a6c6-36f17490b134.jsonl
writer/app_templates/default/.wf/components-root.jsonl
writer/app_templates/default/.wf/components-workflows_root.jsonl
writer/app_templates/default/.wf/components-workflows_workflow-0-lfltcky7l1fsm6j2.jsonl
writer/app_templates/default/.wf/metadata.json
writer/app_templates/default/README.md
writer/app_templates/default/main.py
writer/app_templates/default/requirements.txt
writer/app_templates/default/static/README.md
writer/app_templates/default/static/agent_builder_demo.png
writer/app_templates/default/static/favicon.png
writer/app_templates/hello/.wf/components-blueprints_blueprint-0-t84xyhxau9ej3823.jsonl
writer/app_templates/hello/.wf/components-blueprints_root.jsonl
writer/app_templates/hello/.wf/components-page-0-c0f99a9e-5004-4e75-a6c6-36f17490b134.jsonl
writer/app_templates/hello/.wf/components-root.jsonl
writer/app_templates/hello/.wf/metadata.json
writer/app_templates/hello/main.py
writer/app_templates/hello/static/README.md
writer/app_templates/hello/static/favicon.png
writer/app_templates/hello/static/welcome.svg
writer/audit_and_fix.py
writer/auth.py
writer/autogen.py
writer/blocks/__init__.py
writer/blocks/addtostatelist.py
writer/blocks/apitrigger.py
writer/blocks/base_block.py
writer/blocks/base_trigger.py
writer/blocks/calleventhandler.py
writer/blocks/changepage.py
writer/blocks/code.py
writer/blocks/crontrigger.py
writer/blocks/foreach.py
writer/blocks/httprequest.py
writer/blocks/ifelse.py
writer/blocks/logmessage.py
writer/blocks/parsejson.py
writer/blocks/returnvalue.py
writer/blocks/runblueprint.py
writer/blocks/setstate.py
writer/blocks/sharedblueprint.py
writer/blocks/uieventtrigger.py
writer-1.25.0.dist-info/METADATA
writer-1.25.0.dist-info/WHEEL
writer-1.25.0.dist-info/entry_points.txt
writer-1.25.0.dist-info/licenses/LICENSE.txt
writer-1.25.0.dist-info/RECORD
