Metadata-Version: 2.4
Name: writer
Version: 1.25.0
Summary: An open-source, Python framework for building feature-rich apps that are fully integrated with the Writer platform.
License-File: LICENSE.txt
Keywords: data apps,gui,ui,framework,writer framework
Author: Writer, Inc.
Requires-Python: >=3.9.2,<4.0
Classifier: Development Status :: 5 - Production/Stable
Classifier: Programming Language :: Python :: 3
Classifier: Programming Language :: Python :: 3.10
Classifier: Programming Language :: Python :: 3.11
Classifier: Programming Language :: Python :: 3.12
Classifier: Programming Language :: Python :: 3.13
Classifier: Programming Language :: Python :: 3.14
Classifier: Programming Language :: Python :: 3.9
Provides-Extra: redis
Requires-Dist: authlib (>=1.3.0,<1.7)
Requires-Dist: click (>=8.1.7,<9.0.0)
Requires-Dist: fastapi (>=0.89.1,<1)
Requires-Dist: gitignore-parser (>=0.1.11,<0.2.0)
Requires-Dist: jinja2 (>=3.1.4,<4.0.0)
Requires-Dist: numpy (<=2.0.2) ; python_version < "3.10"
Requires-Dist: numpy (>=2.0,<3.0) ; python_version >= "3.10"
Requires-Dist: orjson (>=3.11.0,<4.0.0)
Requires-Dist: pandas (>=2.2.0,<3)
Requires-Dist: plotly (>=5.24.1,<6.0.0)
Requires-Dist: pyarrow (>=15.0.0,<19.0.0)
Requires-Dist: pydantic (>=2.6.0,<3)
Requires-Dist: python-dateutil (>=2.9.0.post0,<3.0.0)
Requires-Dist: python-multipart (>=0.0.7,<1)
Requires-Dist: pytz (>=2024.1,<2025.0)
Requires-Dist: requests (>=2.31.0,<2.33)
Requires-Dist: uvicorn (>=0.20.0,<1)
Requires-Dist: watchdog (>=3.0.0,<4)
Requires-Dist: websockets (>=12,<16)
Requires-Dist: writer-sdk (>=2.3.1,<3)
Project-URL: Documentation, https://dev.writer.com/framework
Project-URL: Homepage, https://www.writer.com
Project-URL: Repository, https://github.com/writer/writer-framework
